LICENSE
README.md
setup.py
MultiWrapperProject/__init__.py
MultiWrapperProject/e621.py
MultiWrapperProject/gelbooru.py
MultiWrapperProject/hypnohub.py
MultiWrapperProject/rule34.py
MultiWrapperProject.egg-info/PKG-INFO
MultiWrapperProject.egg-info/SOURCES.txt
MultiWrapperProject.egg-info/dependency_links.txt
MultiWrapperProject.egg-info/requires.txt
MultiWrapperProject.egg-info/top_level.txt