Metadata-Version: 2.1
Name: MultiWrapperProject
Version: 0.1.0
Summary: A multi wrapper api project
Home-page: UNKNOWN
Author: philou404
Author-email: <philouerror404@gmail.com>
License: UNKNOWN
Keywords: python,wrapper,e621,furry,yiff,hentai,rule34,gelbooru
Platform: UNKNOWN
Classifier: Programming Language :: Python :: 3
Classifier: Operating System :: Unix
Classifier: Operating System :: MacOS :: MacOS X
Classifier: Operating System :: Microsoft :: Windows
License-File: LICENSE
